LICENSE.txt
MANIFEST.in
README.md
pyproject.toml
setup.py
PyDAQmx/DAQmxCallBack.py
PyDAQmx/DAQmxConfig.py
PyDAQmx/DAQmxConstants.py
PyDAQmx/DAQmxFunctions.py
PyDAQmx/DAQmxTypes.py
PyDAQmx/Task.py
PyDAQmx/__init__.py
PyDAQmx.egg-info/PKG-INFO
PyDAQmx.egg-info/SOURCES.txt
PyDAQmx.egg-info/dependency_links.txt
PyDAQmx.egg-info/top_level.txt
PyDAQmx/example/AnalogInput_acq_IntClk.py
PyDAQmx/example/ContinuousPulseTrainGeneration.py
PyDAQmx/example/MultiChannelAnalogInput.py
PyDAQmx/example/__init__.py
PyDAQmx/example/callback.py
PyDAQmx/example/callback_Task.py
PyDAQmx/example/callback_Task_synchronous.py
PyDAQmx/example/callback_oo.py
PyDAQmx/example/callback_test_unregister.py
PyDAQmx/example/test/__init__.py
PyDAQmx/example/test/test_MultiChannelAnalogInput.py