Metadata-Version: 2.1
Name: PyDAQmx
Version: 1.4.7
Summary: Interface to the National Instruments PyDAQmx driver
Home-page: http://pythonhosted.org/PyDAQmx/
Author: Pierre Cladé
Author-email: pierre.clade@spectro.jussieu.fr
Maintainer: Pierre Cladé
Maintainer-email: pierre.clade@spectro.jussieu.fr
License: This software can be used under one of the following two licenses: (1) The BSD license. (2) Any other license, as long as it is obtained from the original author.
Keywords: DAQmx,National Instrument,Data Acquisition,nidaq,nidaqmx
Classifier: Development Status :: 4 - Beta
Classifier: Intended Audience :: Developers
Classifier: Intended Audience :: Education
Classifier: Intended Audience :: Other Audience
Classifier: Intended Audience :: Science/Research
Classifier: License :: OSI Approved :: BSD License
Classifier: Programming Language :: Python
Classifier: Programming Language :: Python :: 2.7
Classifier: Programming Language :: Python :: 3
Classifier: Topic :: Scientific/Engineering
Classifier: Topic :: Scientific/Engineering :: Physics
Classifier: Topic :: Software Development
Classifier: Topic :: Software Development :: Libraries
Classifier: Topic :: Software Development :: Libraries :: Python Modules
License-File: LICENSE.txt
